<?xml version="1.0" encoding="UTF-8"?>
<!--Sample XML file generated by XMLSpy v2016 rel. 2 sp1 (x64) (http://www.altova.com)-->
<ns1:KliniskProstataStraale xmlns:xsi="http://www.w3.org/2001/XMLSchema-instance" xmlns:ns1="http://www.kreftregisteret.no/kremt/KliniskProstataStraale/v4_0" xsi:schemaLocation="http://www.kreftregisteret.no/kremt/KliniskProstataStraale/v4_0 ../src/main/resources/Prostatapakke/KliniskProstataStraalebehandling_v4_0.xsd">
	<ns1:Meldingsinformasjon>
		<ns1:Skjema>KliniskProstataStraale</ns1:Skjema>
		<ns1:VersjonsNr>4.0</ns1:VersjonsNr>
		<ns1:VersjonsNrOriginal>String</ns1:VersjonsNrOriginal>
		<ns1:KRG_GUID/>
		<ns1:VersjonIP>0</ns1:VersjonIP>
		<ns1:VersjonBT>0</ns1:VersjonBT>
		<ns1:TidspunktSubmit>2001-12-17T09:30:47Z</ns1:TidspunktSubmit>
		<ns1:Brukernavn/>
		<ns1:Filnavn/>
		<ns1:VersjonInternEkstern>0</ns1:VersjonInternEkstern>
	</ns1:Meldingsinformasjon>
	<ns1:Navigering>
		<ns1:Meldingstittel>String</ns1:Meldingstittel>
		<ns1:MeldingsNr/>
	</ns1:Navigering>
	<ns1:StdInfo>
		<ns1:PasientInstitusjon>
			<ns1:FodselsnummerKRG/>
			<ns1:FodselsnummerHF/>
			<ns1:FodselnummerUtland>true</ns1:FodselnummerUtland>
			<ns1:FodselsnummerUtlandSpesifiser>String</ns1:FodselsnummerUtlandSpesifiser>
			<ns1:NavnPasient>String</ns1:NavnPasient>
			<ns1:Sykehuskode/>
			<ns1:SykehusnavnHF/>
			<ns1:SykehusnavnHFSpesifiser/>
			<ns1:SykehusnavnKRGSpesifiser/>
			<ns1:Avdelingskode/>
			<ns1:Avdelingsnavn>14</ns1:Avdelingsnavn>
			<ns1:AvdelingsnavnHFSpesifiser/>
			<ns1:AvdelingsnavnKRGSpesifiser/>
		</ns1:PasientInstitusjon>
		<ns1:Kommentarfelt>
			<ns1:Kommentar/>
		</ns1:Kommentarfelt>
		<ns1:FilmBilde>
			<ns1:FilmNr/>
			<ns1:BildeNr/>
		</ns1:FilmBilde>
		<ns1:Melder>
			<ns1:MeldersNavn/>
			<ns1:MeldeDato>1957-08-13</ns1:MeldeDato>
			<ns1:MelderID/>
		</ns1:Melder>
	</ns1:StdInfo>
	<ns1:Behandling>
		<ns1:PrimaerEllerPostop>1</ns1:PrimaerEllerPostop>
		<ns1:PreStraaleInformasjon>
			<ns1:AktivMonitorering>1</ns1:AktivMonitorering>
			<ns1:RevurderingSykdomsutrbredelse>1</ns1:RevurderingSykdomsutrbredelse>
			<ns1:PreStraalePSAVerdi/>
			<ns1:PreStraalePSAVerdiUkjent/>
			<ns1:EndokrinBehandling>1</ns1:EndokrinBehandling>
			<ns1:DatoOppstartEndokrinBeh>1957-08-13</ns1:DatoOppstartEndokrinBeh>
			<ns1:DatoOppstartEndokrinBehUkjent/>
			<ns1:VarighetEndokrinBehandling/>
			<ns1:VarighetEndokrinBehUkjent/>
		</ns1:PreStraaleInformasjon>
		<ns1:Sykdomsutbredelse>
			<ns1:Tumor>
				<ns1:PalpatoriskTumorHoyre>4</ns1:PalpatoriskTumorHoyre>
				<ns1:PalpatoriskTumorVenstre>4</ns1:PalpatoriskTumorVenstre>
				<ns1:SamletPalpatoriskTumor/>
				<ns1:MRDiagnostikk/>
				<ns1:DatoMRDiagnostikk>1957-08-13</ns1:DatoMRDiagnostikk>
				<ns1:DatoMRDiagnostikkUkjent>99</ns1:DatoMRDiagnostikkUkjent>
				<ns1:PIRADSHoyre>99</ns1:PIRADSHoyre>
				<ns1:PIRADSVenstre>4</ns1:PIRADSVenstre>
				<ns1:MRBasertKliniskTHoyre>4</ns1:MRBasertKliniskTHoyre>
				<ns1:MRBasertKliniskTVenstre>3</ns1:MRBasertKliniskTVenstre>
				<ns1:SamletMRBasertKliniskT/>
				<ns1:TotalVurderingKliniskT>2b</ns1:TotalVurderingKliniskT>
				<ns1:KliniskVurdertAv>2</ns1:KliniskVurdertAv>
			</ns1:Tumor>
			<ns1:RegionaleLK>
				<ns1:RegionaleLKPaavist/>
			</ns1:RegionaleLK>
			<ns1:Fjernmetastaser>
				<ns1:FjernmetPaavist>2</ns1:FjernmetPaavist>
				<ns1:LokalisasjonFjernmet>
					<ns1:FjerneLKmet>true</ns1:FjerneLKmet>
					<ns1:Skjelettmet>true</ns1:Skjelettmet>
					<ns1:AnnetFjernmet>true</ns1:AnnetFjernmet>
					<ns1:AnnetFjernmetSpesifiser/>
				</ns1:LokalisasjonFjernmet>
			</ns1:Fjernmetastaser>
			<ns1:UtredningsmetodeMetastaser>
				<ns1:UtredningsmetodeLK>1</ns1:UtredningsmetodeLK>
				<ns1:AnnenDiagnostikkLKSpesifiser/>
				<ns1:UtredningsmetodeFjernmet>
					<ns1:SkjelettscintigrafiMet>true</ns1:SkjelettscintigrafiMet>
					<ns1:RtgThoraxMet>true</ns1:RtgThoraxMet>
					<ns1:RtgBekkenMet>true</ns1:RtgBekkenMet>
					<ns1:CTMet>true</ns1:CTMet>
					<ns1:MRMet>true</ns1:MRMet>
					<ns1:PETMet>true</ns1:PETMet>
					<ns1:CytologiMet>true</ns1:CytologiMet>
					<ns1:BiopsiMet>true</ns1:BiopsiMet>
					<ns1:AnnenDiagnostikkMet>true</ns1:AnnenDiagnostikkMet>
					<ns1:AnnenDiagnostikkMetSpesifiser/>
					<ns1:UtredningsmetodeFjernmetUkjent/>
				</ns1:UtredningsmetodeFjernmet>
			</ns1:UtredningsmetodeMetastaser>
		</ns1:Sykdomsutbredelse>
		<ns1:Straalebehandling>
			<ns1:EksternStraalebehandling>0</ns1:EksternStraalebehandling>
			<ns1:DatoOppstartStraale>1957-08-13</ns1:DatoOppstartStraale>
			<ns1:Prostata>
				<ns1:ProstataFRDoseGY/>
				<ns1:ProstataFRDoseUkjent>99</ns1:ProstataFRDoseUkjent>
				<ns1:ProstataAntFR/>
				<ns1:ProstataAntFRUkjent>99</ns1:ProstataAntFRUkjent>
			</ns1:Prostata>
			<ns1:LKbekken>
				<ns1:LKBekkenStraalebehandling>0</ns1:LKBekkenStraalebehandling>
			</ns1:LKbekken>
			<ns1:HoydoserateBrachyterapi>
				<ns1:HDBrachyterapi/>
				<ns1:HDBrachyterapiFRDoseGY/>
				<ns1:HDBrachyterapiFRDoseUkjent/>
				<ns1:HDBrachyterapiAntFR/>
				<ns1:HDBrachyterapiAntFRUkjent/>
			</ns1:HoydoserateBrachyterapi>
			<ns1:LavdoserateBrachyterapi>
				<ns1:LDBrachyterapi>0</ns1:LDBrachyterapi>
				<ns1:Behandlingssted/>
				<ns1:BehandlingsstedUkjent>99</ns1:BehandlingsstedUkjent>
				<ns1:LDBrachyterapiFRDoseGY/>
				<ns1:LDBrachyterapiFRDoseUkjent>99</ns1:LDBrachyterapiFRDoseUkjent>
			</ns1:LavdoserateBrachyterapi>
		</ns1:Straalebehandling>
	</ns1:Behandling>
</ns1:KliniskProstataStraale>
